durationwidget/__init__.py
durationwidget/apps.py
durationwidget/widgets.py
durationwidget/migrations/__init__.py
durationwidget/templates/widgets/duration_multiple_input.html
durationwidget/templates/widgets/labeled_number_input.html
django_durationwidget-1.0.5.dist-info/LICENSE
django_durationwidget-1.0.5.dist-info/METADATA
django_durationwidget-1.0.5.dist-info/WHEEL
django_durationwidget-1.0.5.dist-info/top_level.txt
django_durationwidget-1.0.5.dist-info/RECORD
