Metadata-Version: 2.1
Name: django-durationwidget
Version: 1.0.5
Summary: Django Duration field widget to handle duration field in the form
Home-page: https://github.com/devangpadhiyar/django-durationwidget
Author: Devang Padhiyar
Author-email: devangpadhiyar700@gmail.com
License: UNKNOWN
Platform: UNKNOWN
Classifier: Programming Language :: Python :: 3
Classifier: License :: OSI Approved :: MIT License
Classifier: Operating System :: OS Independent
